{
  "version": "6",
  "dialect": "sqlite",
  "id": "72800670-e48f-469a-874e-d0269378cd5a",
  "prevId": "b1131935-981f-4a7d-8d3e-b70467c157e5",
  "tables": {
    "activities": {
      "name": "activities",
      "columns": {
        "id": {
          "name": "id",
          "type": "integer",
          "primaryKey": true,
          "notNull": true,
          "autoincrement": true
        },
        "user_id": {
          "name": "user_id",
          "type": "integer",
          "primaryKey": false,
          "notNull": true,
          "autoincrement": false
        },
        "datum": {
          "name": "datum",
          "type": "text",
          "primaryKey": false,
          "notNull": true,
          "autoincrement": false
        },
        "type": {
          "name": "type",
          "type": "text",
          "primaryKey": false,
          "notNull": false,
          "autoincrement": false
        },
        "naam": {
          "name": "naam",
          "type": "text",
          "primaryKey": false,
          "notNull": false,
          "autoincrement": false
        },
        "duur_min": {
          "name": "duur_min",
          "type": "integer",
          "primaryKey": false,
          "notNull": false,
          "autoincrement": false
        },
        "afstand_km": {
          "name": "afstand_km",
          "type": "real",
          "primaryKey": false,
          "notNull": false,
          "autoincrement": false
        },
        "gem_w": {
          "name": "gem_w",
          "type": "integer",
          "primaryKey": false,
          "notNull": false,
          "autoincrement": false
        },
        "norm_w": {
          "name": "norm_w",
          "type": "integer",
          "primaryKey": false,
          "notNull": false,
          "autoincrement": false
        },
        "if_pct": {
          "name": "if_pct",
          "type": "real",
          "primaryKey": false,
          "notNull": false,
          "autoincrement": false
        },
        "tss": {
          "name": "tss",
          "type": "integer",
          "primaryKey": false,
          "notNull": false,
          "autoincrement": false
        },
        "gem_hr": {
          "name": "gem_hr",
          "type": "integer",
          "primaryKey": false,
          "notNull": false,
          "autoincrement": false
        },
        "max_hr": {
          "name": "max_hr",
          "type": "integer",
          "primaryKey": false,
          "notNull": false,
          "autoincrement": false
        },
        "pi": {
          "name": "pi",
          "type": "real",
          "primaryKey": false,
          "notNull": false,
          "autoincrement": false
        },
        "ftp": {
          "name": "ftp",
          "type": "integer",
          "primaryKey": false,
          "notNull": false,
          "autoincrement": false
        },
        "gewicht": {
          "name": "gewicht",
          "type": "real",
          "primaryKey": false,
          "notNull": false,
          "autoincrement": false
        },
        "rolling_ftp": {
          "name": "rolling_ftp",
          "type": "integer",
          "primaryKey": false,
          "notNull": false,
          "autoincrement": false
        },
        "zone_times_json": {
          "name": "zone_times_json",
          "type": "text",
          "primaryKey": false,
          "notNull": false,
          "autoincrement": false
        },
        "activity_id_ext": {
          "name": "activity_id_ext",
          "type": "text",
          "primaryKey": false,
          "notNull": false,
          "autoincrement": false
        }
      },
      "indexes": {
        "activities_user_actid_unq": {
          "name": "activities_user_actid_unq",
          "columns": [
            "user_id",
            "activity_id_ext"
          ],
          "isUnique": true
        },
        "activities_user_datum_idx": {
          "name": "activities_user_datum_idx",
          "columns": [
            "user_id",
            "datum"
          ],
          "isUnique": false
        }
      },
      "foreignKeys": {
        "activities_user_id_users_id_fk": {
          "name": "activities_user_id_users_id_fk",
          "tableFrom": "activities",
          "tableTo": "users",
          "columnsFrom": [
            "user_id"
          ],
          "columnsTo": [
            "id"
          ],
          "onDelete": "no action",
          "onUpdate": "no action"
        }
      },
      "compositePrimaryKeys": {},
      "uniqueConstraints": {},
      "checkConstraints": {}
    },
    "checkins": {
      "name": "checkins",
      "columns": {
        "user_id": {
          "name": "user_id",
          "type": "integer",
          "primaryKey": false,
          "notNull": true,
          "autoincrement": false
        },
        "datum": {
          "name": "datum",
          "type": "text",
          "primaryKey": false,
          "notNull": true,
          "autoincrement": false
        },
        "slaap": {
          "name": "slaap",
          "type": "text",
          "primaryKey": false,
          "notNull": false,
          "autoincrement": false
        },
        "benen": {
          "name": "benen",
          "type": "text",
          "primaryKey": false,
          "notNull": false,
          "autoincrement": false
        },
        "stress": {
          "name": "stress",
          "type": "text",
          "primaryKey": false,
          "notNull": false,
          "autoincrement": false
        },
        "ts": {
          "name": "ts",
          "type": "text",
          "primaryKey": false,
          "notNull": false,
          "autoincrement": false
        }
      },
      "indexes": {},
      "foreignKeys": {
        "checkins_user_id_users_id_fk": {
          "name": "checkins_user_id_users_id_fk",
          "tableFrom": "checkins",
          "tableTo": "users",
          "columnsFrom": [
            "user_id"
          ],
          "columnsTo": [
            "id"
          ],
          "onDelete": "no action",
          "onUpdate": "no action"
        }
      },
      "compositePrimaryKeys": {
        "checkins_user_id_datum_pk": {
          "columns": [
            "user_id",
            "datum"
          ],
          "name": "checkins_user_id_datum_pk"
        }
      },
      "uniqueConstraints": {},
      "checkConstraints": {}
    },
    "day_state": {
      "name": "day_state",
      "columns": {
        "user_id": {
          "name": "user_id",
          "type": "integer",
          "primaryKey": false,
          "notNull": true,
          "autoincrement": false
        },
        "datum": {
          "name": "datum",
          "type": "text",
          "primaryKey": false,
          "notNull": true,
          "autoincrement": false
        },
        "override_json": {
          "name": "override_json",
          "type": "text",
          "primaryKey": false,
          "notNull": false,
          "autoincrement": false
        },
        "disposition": {
          "name": "disposition",
          "type": "text",
          "primaryKey": false,
          "notNull": false,
          "autoincrement": false
        }
      },
      "indexes": {},
      "foreignKeys": {
        "day_state_user_id_users_id_fk": {
          "name": "day_state_user_id_users_id_fk",
          "tableFrom": "day_state",
          "tableTo": "users",
          "columnsFrom": [
            "user_id"
          ],
          "columnsTo": [
            "id"
          ],
          "onDelete": "no action",
          "onUpdate": "no action"
        }
      },
      "compositePrimaryKeys": {
        "day_state_user_id_datum_pk": {
          "columns": [
            "user_id",
            "datum"
          ],
          "name": "day_state_user_id_datum_pk"
        }
      },
      "uniqueConstraints": {},
      "checkConstraints": {}
    },
    "events": {
      "name": "events",
      "columns": {
        "id": {
          "name": "id",
          "type": "integer",
          "primaryKey": true,
          "notNull": true,
          "autoincrement": true
        },
        "user_id": {
          "name": "user_id",
          "type": "integer",
          "primaryKey": false,
          "notNull": true,
          "autoincrement": false
        },
        "datum": {
          "name": "datum",
          "type": "text",
          "primaryKey": false,
          "notNull": true,
          "autoincrement": false
        },
        "naam": {
          "name": "naam",
          "type": "text",
          "primaryKey": false,
          "notNull": false,
          "autoincrement": false
        },
        "type": {
          "name": "type",
          "type": "text",
          "primaryKey": false,
          "notNull": false,
          "autoincrement": false
        },
        "prioriteit": {
          "name": "prioriteit",
          "type": "text",
          "primaryKey": false,
          "notNull": false,
          "autoincrement": false
        },
        "afstand_km": {
          "name": "afstand_km",
          "type": "real",
          "primaryKey": false,
          "notNull": false,
          "autoincrement": false
        },
        "hoogtemeters": {
          "name": "hoogtemeters",
          "type": "integer",
          "primaryKey": false,
          "notNull": false,
          "autoincrement": false
        },
        "klim_type": {
          "name": "klim_type",
          "type": "text",
          "primaryKey": false,
          "notNull": false,
          "autoincrement": false
        },
        "notitie": {
          "name": "notitie",
          "type": "text",
          "primaryKey": false,
          "notNull": false,
          "autoincrement": false
        }
      },
      "indexes": {
        "events_user_datum_idx": {
          "name": "events_user_datum_idx",
          "columns": [
            "user_id",
            "datum"
          ],
          "isUnique": false
        }
      },
      "foreignKeys": {
        "events_user_id_users_id_fk": {
          "name": "events_user_id_users_id_fk",
          "tableFrom": "events",
          "tableTo": "users",
          "columnsFrom": [
            "user_id"
          ],
          "columnsTo": [
            "id"
          ],
          "onDelete": "no action",
          "onUpdate": "no action"
        }
      },
      "compositePrimaryKeys": {},
      "uniqueConstraints": {},
      "checkConstraints": {}
    },
    "planner_days": {
      "name": "planner_days",
      "columns": {
        "id": {
          "name": "id",
          "type": "integer",
          "primaryKey": true,
          "notNull": true,
          "autoincrement": true
        },
        "user_id": {
          "name": "user_id",
          "type": "integer",
          "primaryKey": false,
          "notNull": true,
          "autoincrement": false
        },
        "datum": {
          "name": "datum",
          "type": "text",
          "primaryKey": false,
          "notNull": true,
          "autoincrement": false
        },
        "train": {
          "name": "train",
          "type": "integer",
          "primaryKey": false,
          "notNull": false,
          "autoincrement": false
        },
        "dag": {
          "name": "dag",
          "type": "text",
          "primaryKey": false,
          "notNull": false,
          "autoincrement": false
        },
        "minuten": {
          "name": "minuten",
          "type": "integer",
          "primaryKey": false,
          "notNull": false,
          "autoincrement": false
        },
        "dagtype": {
          "name": "dagtype",
          "type": "text",
          "primaryKey": false,
          "notNull": false,
          "autoincrement": false
        },
        "toelichting": {
          "name": "toelichting",
          "type": "text",
          "primaryKey": false,
          "notNull": false,
          "autoincrement": false
        },
        "voorgesteld_type": {
          "name": "voorgesteld_type",
          "type": "text",
          "primaryKey": false,
          "notNull": false,
          "autoincrement": false
        },
        "gedaan": {
          "name": "gedaan",
          "type": "integer",
          "primaryKey": false,
          "notNull": false,
          "autoincrement": false
        }
      },
      "indexes": {
        "planner_days_user_datum_unq": {
          "name": "planner_days_user_datum_unq",
          "columns": [
            "user_id",
            "datum"
          ],
          "isUnique": true
        }
      },
      "foreignKeys": {
        "planner_days_user_id_users_id_fk": {
          "name": "planner_days_user_id_users_id_fk",
          "tableFrom": "planner_days",
          "tableTo": "users",
          "columnsFrom": [
            "user_id"
          ],
          "columnsTo": [
            "id"
          ],
          "onDelete": "no action",
          "onUpdate": "no action"
        }
      },
      "compositePrimaryKeys": {},
      "uniqueConstraints": {},
      "checkConstraints": {}
    },
    "power_curve_cache": {
      "name": "power_curve_cache",
      "columns": {
        "id": {
          "name": "id",
          "type": "integer",
          "primaryKey": true,
          "notNull": true,
          "autoincrement": true
        },
        "user_id": {
          "name": "user_id",
          "type": "integer",
          "primaryKey": false,
          "notNull": true,
          "autoincrement": false
        },
        "window": {
          "name": "window",
          "type": "text",
          "primaryKey": false,
          "notNull": true,
          "autoincrement": false
        },
        "fetched_on": {
          "name": "fetched_on",
          "type": "text",
          "primaryKey": false,
          "notNull": true,
          "autoincrement": false
        },
        "raw_json": {
          "name": "raw_json",
          "type": "text",
          "primaryKey": false,
          "notNull": true,
          "autoincrement": false
        }
      },
      "indexes": {
        "power_curve_cache_user_window_unq": {
          "name": "power_curve_cache_user_window_unq",
          "columns": [
            "user_id",
            "window"
          ],
          "isUnique": true
        }
      },
      "foreignKeys": {
        "power_curve_cache_user_id_users_id_fk": {
          "name": "power_curve_cache_user_id_users_id_fk",
          "tableFrom": "power_curve_cache",
          "tableTo": "users",
          "columnsFrom": [
            "user_id"
          ],
          "columnsTo": [
            "id"
          ],
          "onDelete": "no action",
          "onUpdate": "no action"
        }
      },
      "compositePrimaryKeys": {},
      "uniqueConstraints": {},
      "checkConstraints": {}
    },
    "rpe": {
      "name": "rpe",
      "columns": {
        "user_id": {
          "name": "user_id",
          "type": "integer",
          "primaryKey": false,
          "notNull": true,
          "autoincrement": false
        },
        "datum": {
          "name": "datum",
          "type": "text",
          "primaryKey": false,
          "notNull": true,
          "autoincrement": false
        },
        "rpe": {
          "name": "rpe",
          "type": "integer",
          "primaryKey": false,
          "notNull": false,
          "autoincrement": false
        }
      },
      "indexes": {},
      "foreignKeys": {
        "rpe_user_id_users_id_fk": {
          "name": "rpe_user_id_users_id_fk",
          "tableFrom": "rpe",
          "tableTo": "users",
          "columnsFrom": [
            "user_id"
          ],
          "columnsTo": [
            "id"
          ],
          "onDelete": "no action",
          "onUpdate": "no action"
        }
      },
      "compositePrimaryKeys": {
        "rpe_user_id_datum_pk": {
          "columns": [
            "user_id",
            "datum"
          ],
          "name": "rpe_user_id_datum_pk"
        }
      },
      "uniqueConstraints": {},
      "checkConstraints": {}
    },
    "settings": {
      "name": "settings",
      "columns": {
        "user_id": {
          "name": "user_id",
          "type": "integer",
          "primaryKey": true,
          "notNull": true,
          "autoincrement": false
        },
        "ftp": {
          "name": "ftp",
          "type": "integer",
          "primaryKey": false,
          "notNull": false,
          "autoincrement": false
        },
        "hr_max": {
          "name": "hr_max",
          "type": "integer",
          "primaryKey": false,
          "notNull": false,
          "autoincrement": false
        },
        "hr_rest": {
          "name": "hr_rest",
          "type": "integer",
          "primaryKey": false,
          "notNull": false,
          "autoincrement": false
        },
        "lthr": {
          "name": "lthr",
          "type": "integer",
          "primaryKey": false,
          "notNull": false,
          "autoincrement": false
        },
        "threshold_pace": {
          "name": "threshold_pace",
          "type": "text",
          "primaryKey": false,
          "notNull": false,
          "autoincrement": false
        },
        "doel": {
          "name": "doel",
          "type": "text",
          "primaryKey": false,
          "notNull": false,
          "autoincrement": false
        },
        "doel_start": {
          "name": "doel_start",
          "type": "text",
          "primaryKey": false,
          "notNull": false,
          "autoincrement": false
        },
        "doel_duur": {
          "name": "doel_duur",
          "type": "integer",
          "primaryKey": false,
          "notNull": false,
          "autoincrement": false
        },
        "fase": {
          "name": "fase",
          "type": "text",
          "primaryKey": false,
          "notNull": false,
          "autoincrement": false
        },
        "gewicht": {
          "name": "gewicht",
          "type": "real",
          "primaryKey": false,
          "notNull": false,
          "autoincrement": false
        },
        "profiel_preset": {
          "name": "profiel_preset",
          "type": "text",
          "primaryKey": false,
          "notNull": false,
          "autoincrement": false
        },
        "coach_naam": {
          "name": "coach_naam",
          "type": "text",
          "primaryKey": false,
          "notNull": false,
          "autoincrement": false
        },
        "coach_persona": {
          "name": "coach_persona",
          "type": "text",
          "primaryKey": false,
          "notNull": false,
          "autoincrement": false
        },
        "naam": {
          "name": "naam",
          "type": "text",
          "primaryKey": false,
          "notNull": false,
          "autoincrement": false
        },
        "week_uren": {
          "name": "week_uren",
          "type": "integer",
          "primaryKey": false,
          "notNull": false,
          "autoincrement": false
        },
        "pendel_duur_min": {
          "name": "pendel_duur_min",
          "type": "integer",
          "primaryKey": false,
          "notNull": false,
          "autoincrement": false
        },
        "pendel_aantal": {
          "name": "pendel_aantal",
          "type": "integer",
          "primaryKey": false,
          "notNull": false,
          "autoincrement": false
        },
        "ftp_auto_update": {
          "name": "ftp_auto_update",
          "type": "integer",
          "primaryKey": false,
          "notNull": false,
          "autoincrement": false
        },
        "weight_auto_update": {
          "name": "weight_auto_update",
          "type": "integer",
          "primaryKey": false,
          "notNull": false,
          "autoincrement": false
        },
        "email_digest": {
          "name": "email_digest",
          "type": "text",
          "primaryKey": false,
          "notNull": false,
          "autoincrement": false
        }
      },
      "indexes": {},
      "foreignKeys": {
        "settings_user_id_users_id_fk": {
          "name": "settings_user_id_users_id_fk",
          "tableFrom": "settings",
          "tableTo": "users",
          "columnsFrom": [
            "user_id"
          ],
          "columnsTo": [
            "id"
          ],
          "onDelete": "no action",
          "onUpdate": "no action"
        }
      },
      "compositePrimaryKeys": {},
      "uniqueConstraints": {},
      "checkConstraints": {}
    },
    "sync_state": {
      "name": "sync_state",
      "columns": {
        "user_id": {
          "name": "user_id",
          "type": "integer",
          "primaryKey": true,
          "notNull": true,
          "autoincrement": false
        },
        "last_sync": {
          "name": "last_sync",
          "type": "text",
          "primaryKey": false,
          "notNull": false,
          "autoincrement": false
        },
        "meso_week": {
          "name": "meso_week",
          "type": "integer",
          "primaryKey": false,
          "notNull": false,
          "autoincrement": false
        },
        "load_carry": {
          "name": "load_carry",
          "type": "real",
          "primaryKey": false,
          "notNull": false,
          "autoincrement": false
        },
        "ftp_last_sync": {
          "name": "ftp_last_sync",
          "type": "text",
          "primaryKey": false,
          "notNull": false,
          "autoincrement": false
        },
        "weight_last_sync": {
          "name": "weight_last_sync",
          "type": "text",
          "primaryKey": false,
          "notNull": false,
          "autoincrement": false
        },
        "debt_opt_in_week": {
          "name": "debt_opt_in_week",
          "type": "text",
          "primaryKey": false,
          "notNull": false,
          "autoincrement": false
        }
      },
      "indexes": {},
      "foreignKeys": {
        "sync_state_user_id_users_id_fk": {
          "name": "sync_state_user_id_users_id_fk",
          "tableFrom": "sync_state",
          "tableTo": "users",
          "columnsFrom": [
            "user_id"
          ],
          "columnsTo": [
            "id"
          ],
          "onDelete": "no action",
          "onUpdate": "no action"
        }
      },
      "compositePrimaryKeys": {},
      "uniqueConstraints": {},
      "checkConstraints": {}
    },
    "users": {
      "name": "users",
      "columns": {
        "id": {
          "name": "id",
          "type": "integer",
          "primaryKey": true,
          "notNull": true,
          "autoincrement": true
        },
        "email": {
          "name": "email",
          "type": "text",
          "primaryKey": false,
          "notNull": false,
          "autoincrement": false
        },
        "intervals_athlete_id": {
          "name": "intervals_athlete_id",
          "type": "text",
          "primaryKey": false,
          "notNull": false,
          "autoincrement": false
        },
        "created_at": {
          "name": "created_at",
          "type": "text",
          "primaryKey": false,
          "notNull": false,
          "autoincrement": false
        }
      },
      "indexes": {},
      "foreignKeys": {},
      "compositePrimaryKeys": {},
      "uniqueConstraints": {},
      "checkConstraints": {}
    },
    "weekplans": {
      "name": "weekplans",
      "columns": {
        "user_id": {
          "name": "user_id",
          "type": "integer",
          "primaryKey": false,
          "notNull": true,
          "autoincrement": false
        },
        "week_monday": {
          "name": "week_monday",
          "type": "text",
          "primaryKey": false,
          "notNull": true,
          "autoincrement": false
        },
        "entries_json": {
          "name": "entries_json",
          "type": "text",
          "primaryKey": false,
          "notNull": false,
          "autoincrement": false
        }
      },
      "indexes": {},
      "foreignKeys": {
        "weekplans_user_id_users_id_fk": {
          "name": "weekplans_user_id_users_id_fk",
          "tableFrom": "weekplans",
          "tableTo": "users",
          "columnsFrom": [
            "user_id"
          ],
          "columnsTo": [
            "id"
          ],
          "onDelete": "no action",
          "onUpdate": "no action"
        }
      },
      "compositePrimaryKeys": {
        "weekplans_user_id_week_monday_pk": {
          "columns": [
            "user_id",
            "week_monday"
          ],
          "name": "weekplans_user_id_week_monday_pk"
        }
      },
      "uniqueConstraints": {},
      "checkConstraints": {}
    },
    "wellness": {
      "name": "wellness",
      "columns": {
        "id": {
          "name": "id",
          "type": "integer",
          "primaryKey": true,
          "notNull": true,
          "autoincrement": true
        },
        "user_id": {
          "name": "user_id",
          "type": "integer",
          "primaryKey": false,
          "notNull": true,
          "autoincrement": false
        },
        "datum": {
          "name": "datum",
          "type": "text",
          "primaryKey": false,
          "notNull": true,
          "autoincrement": false
        },
        "rhr": {
          "name": "rhr",
          "type": "integer",
          "primaryKey": false,
          "notNull": false,
          "autoincrement": false
        },
        "hrv": {
          "name": "hrv",
          "type": "real",
          "primaryKey": false,
          "notNull": false,
          "autoincrement": false
        },
        "slaap_u": {
          "name": "slaap_u",
          "type": "real",
          "primaryKey": false,
          "notNull": false,
          "autoincrement": false
        },
        "slaap_score": {
          "name": "slaap_score",
          "type": "integer",
          "primaryKey": false,
          "notNull": false,
          "autoincrement": false
        },
        "readiness": {
          "name": "readiness",
          "type": "integer",
          "primaryKey": false,
          "notNull": false,
          "autoincrement": false
        },
        "mood": {
          "name": "mood",
          "type": "text",
          "primaryKey": false,
          "notNull": false,
          "autoincrement": false
        },
        "weight_kg": {
          "name": "weight_kg",
          "type": "real",
          "primaryKey": false,
          "notNull": false,
          "autoincrement": false
        },
        "ctl": {
          "name": "ctl",
          "type": "real",
          "primaryKey": false,
          "notNull": false,
          "autoincrement": false
        },
        "atl": {
          "name": "atl",
          "type": "real",
          "primaryKey": false,
          "notNull": false,
          "autoincrement": false
        },
        "vorm": {
          "name": "vorm",
          "type": "real",
          "primaryKey": false,
          "notNull": false,
          "autoincrement": false
        },
        "ramp": {
          "name": "ramp",
          "type": "real",
          "primaryKey": false,
          "notNull": false,
          "autoincrement": false
        }
      },
      "indexes": {
        "wellness_user_datum_unq": {
          "name": "wellness_user_datum_unq",
          "columns": [
            "user_id",
            "datum"
          ],
          "isUnique": true
        }
      },
      "foreignKeys": {
        "wellness_user_id_users_id_fk": {
          "name": "wellness_user_id_users_id_fk",
          "tableFrom": "wellness",
          "tableTo": "users",
          "columnsFrom": [
            "user_id"
          ],
          "columnsTo": [
            "id"
          ],
          "onDelete": "no action",
          "onUpdate": "no action"
        }
      },
      "compositePrimaryKeys": {},
      "uniqueConstraints": {},
      "checkConstraints": {}
    }
  },
  "views": {},
  "enums": {},
  "_meta": {
    "schemas": {},
    "tables": {},
    "columns": {}
  },
  "internal": {
    "indexes": {}
  }
}